{
    "jumpcd": [
        {
            "id": 685455946390044674,
            "time_rem": 993540
        },
        {
            "id": 450186061558317066,
            "time_rem": 1807320
        },
        {
            "id": 458600891964981258,
            "time_rem": 0
        },
        {
            "id": 433227700660994050,
            "time_rem": 0
        },
        {
            "id": 729752596599930920,
            "time_rem": 603420
        },
        {
            "id": 761983355549777980,
            "time_rem": 2460
        },
        {
            "id": 424216464518807553,
            "time_rem": 7920
        },
        {
            "id": 372950165302280192,
            "time_rem": 0
        },
        {
            "id": 825072142730133504,
            "time_rem": 1467120
        },
        {
            "id": 615953553881694230,
            "time_rem": 0
        },
        {
            "id": 403640732893839361,
            "time_rem": 0
        },
        {
            "id": 394275202323972096,
            "time_rem": 1679640
        },
        {
            "id": 640056743157694466,
            "time_rem": 0
        },
        {
            "id": 677715028417183744,
            "time_rem": 0
        },
        {
            "id": 741829006734655500,
            "time_rem": 290880
        },
        {
            "id": 489848719609430027,
            "time_rem": 1857060
        },
        {
            "id": 791172694439231498,
            "time_rem": 1885560
        },
        {
            "id": 787061202005262368,
            "time_rem": 0
        },
        {
            "id": 818427905381761095,
            "time_rem": 0
        },
        {
            "id": 838508469958475776,
            "time_rem": 1207080
        },
        {
            "id": 795031063414964255,
            "time_rem": 1381320
        },
        {
            "id": 610839799078584320,
            "time_rem": 1344540
        },
        {
            "id": 740942537216491542,
            "time_rem": 1572900
        },
        {
            "id": 645627502668152874,
            "time_rem": 1060560
        },
        {
            "id": 833012749234995231,
            "time_rem": 1828500
        },
        {
            "id": 804072522156212334,
            "time_rem": 1670820
        },
        {
            "id": 737256988601352192,
            "time_rem": 1825080
        },
        {
            "id": 558556520179302401,
            "time_rem": 1415940
        },
        {
            "id": 834462767028895795,
            "time_rem": 870000
        },
        {
            "id": 763561772585713684,
            "time_rem": 1843500
        },
        {
            "id": 466340532789051404,
            "time_rem": 1435380
        },
        {
            "id": 476328125337436171,
            "time_rem": 1470540
        },
        {
            "id": 344500486675759104,
            "time_rem": 1888740
        },
        {
            "id": 172860614606192640,
            "time_rem": 1867740
        },
        {
            "id": 624218005626159115,
            "time_rem": 1455600
        },
        {
            "id": 299575407165046784,
            "time_rem": 1896720
        },
        {
            "id": 638120700401680399,
            "time_rem": 1896360
        },
        {
            "id": 679347073165950987,
            "time_rem": 1898400
        },
        {
            "id": 459128715256004609,
            "time_rem": 1850820
        },
        {
            "id": 263972501850292224,
            "time_rem": 1667760
        },
        {
            "id": 694105351632715776,
            "time_rem": 1865340
        },
        {
            "id": 820787286144450560,
            "time_rem": 1791360
        },
        {
            "id": 638865468001746944,
            "time_rem": 1879080
        },
        {
            "id": 722155322403192962,
            "time_rem": 1523640
        },
        {
            "id": 640639093776187392,
            "time_rem": 1557360
        },
        {
            "id": 409846605013975041,
            "time_rem": 1620060
        },
        {
            "id": 755444414717100042,
            "time_rem": 1556940
        },
        {
            "id": 818921937253302302,
            "time_rem": 0
        },
        {
            "id": 685358965319663667,
            "time_rem": 1799640
        },
        {
            "id": 435473278551851028,
            "time_rem": 1899180
        },
        {
            "id": 361560935564967946,
            "time_rem": 1862040
        },
        {
            "id": 612229781487878171,
            "time_rem": 1803360
        },
        {
            "id": 305420792202526723,
            "time_rem": 1898700
        },
        {
            "id": 627834583169368075,
            "time_rem": 1757520
        },
        {
            "id": 455813761291255818,
            "time_rem": 1876380
        },
        {
            "id": 676169180378169345,
            "time_rem": 1864860
        },
        {
            "id": 684784415049515084,
            "time_rem": 1898580
        },
        {
            "id": 837646953806168074,
            "time_rem": 1771740
        },
        {
            "id": 513369409813741570,
            "time_rem": 1895400
        },
        {
            "id": 848603600719577129,
            "time_rem": 1900080
        },
        {
            "id": 716077110757687377,
            "time_rem": 1900680
        },
        {
            "id": 227163752603058176,
            "time_rem": 1851120
        },
        {
            "id": 378187472770695189,
            "time_rem": 1897920
        },
        {
            "id": 876378582224613416,
            "time_rem": 1892580
        }
    ]
}